gtexquery/__init__.py
gtexquery/data_handling/__init__.py
gtexquery/data_handling/biomart.py
gtexquery/data_handling/process.py
gtexquery/data_handling/request.py
gtexquery/logs/__init__.py
gtexquery/logs/get_logger.py
gtexquery/multithreading/__init__.py
gtexquery/multithreading/request.py
gtexquery-3.0.0.dist-info/LICENSE
gtexquery-3.0.0.dist-info/WHEEL
gtexquery-3.0.0.dist-info/METADATA
gtexquery-3.0.0.dist-info/RECORD
