Metadata-Version: 2.1
Name: gtexquery
Version: 3.0.0
Summary: Code for handling multithreaded queries for GTEx
License: MIT
Author: rbpatt2019
Author-email: rb.patterson.cross@gmail.com
Requires-Python: >=3.9,<4.0
Classifier: Development Status :: 5 - Production/Stable
Classifier: License :: OSI Approved :: MIT License
Classifier: Programming Language :: Python :: 3
Classifier: Programming Language :: Python :: 3.9
Requires-Dist: PyYAML (>=5.4.1)
Requires-Dist: aiohttp (>=3.7.4)
Requires-Dist: lxml (>=4.6.3,<5.0.0)
Requires-Dist: openpyxl (>=3.0.7,<4.0.0)
Requires-Dist: pandas (>=1.3.0,<2.0.0)
Requires-Dist: requests (>=2.25.1,<3.0.0)
